easy_vector/__init__.py
easy_vector/vector.py
easy_vector-0.1.0.dist-info/DESCRIPTION.rst
easy_vector-0.1.0.dist-info/METADATA
easy_vector-0.1.0.dist-info/RECORD
easy_vector-0.1.0.dist-info/WHEEL
easy_vector-0.1.0.dist-info/metadata.json
easy_vector-0.1.0.dist-info/top_level.txt
