Metadata-Version: 2.0
Name: easy-vector
Version: 0.1.0
Summary: Vectors. Pure, Pythonic.
Home-page: https://github.com/DariusMontez/easy_vector
Author: Darius Montez
Author-email: darius.montez@gmail.com
License: MIT license
Keywords: easy_vector
Platform: UNKNOWN
Classifier: Development Status :: 2 - Pre-Alpha
Classifier: Intended Audience :: Developers
Classifier: License :: OSI Approved :: MIT License
Classifier: Natural Language :: English
Classifier: Programming Language :: Python :: 2
Classifier: Programming Language :: Python :: 2.7
Classifier: Programming Language :: Python :: 3
Classifier: Programming Language :: Python :: 3.4
Classifier: Programming Language :: Python :: 3.5
Classifier: Programming Language :: Python :: 3.6
